liualgotrader/__init__.py
liualgotrader/analytics/__init__.py
liualgotrader/analytics/analysis.py
liualgotrader/analytics/consolidate.py
liualgotrader/backtesting/optimizer.py
liualgotrader/common/__init__.py
liualgotrader/common/assets.py
liualgotrader/common/concurrency.py
liualgotrader/common/config.py
liualgotrader/common/data_loader.py
liualgotrader/common/database.py
liualgotrader/common/decorators.py
liualgotrader/common/exceptions.py
liualgotrader/common/hyperparameter.py
liualgotrader/common/list_utils.py
liualgotrader/common/market_data.py
liualgotrader/common/tlog.py
liualgotrader/common/trading_data.py
liualgotrader/common/types.py
liualgotrader/consumer.py
liualgotrader/data/__init__.py
liualgotrader/data/alpaca.py
liualgotrader/data/data_base.py
liualgotrader/data/data_factory.py
liualgotrader/data/finnhub.py
liualgotrader/data/gemini.py
liualgotrader/data/polygon.py
liualgotrader/data/static.py
liualgotrader/data/streaming_base.py
liualgotrader/data/tradier.py
liualgotrader/enhanced_backtest.py
liualgotrader/fincalcs/__init__.py
liualgotrader/fincalcs/candle_patterns.py
liualgotrader/fincalcs/data_conditions.py
liualgotrader/fincalcs/resample.py
liualgotrader/fincalcs/support_resistance.py
liualgotrader/fincalcs/trends.py
liualgotrader/fincalcs/vwap.py
liualgotrader/miners/__init__.py
liualgotrader/miners/base.py
liualgotrader/miners/gainloss.py
liualgotrader/miners/stock_cluster.py
liualgotrader/models/__init__.py
liualgotrader/models/accounts.py
liualgotrader/models/algo_run.py
liualgotrader/models/gain_loss.py
liualgotrader/models/keystore.py
liualgotrader/models/new_trades.py
liualgotrader/models/optimizer.py
liualgotrader/models/portfolio.py
liualgotrader/models/ticker_data.py
liualgotrader/models/ticker_snapshot.py
liualgotrader/models/tradeplan.py
liualgotrader/models/trades.py
liualgotrader/models/trending_tickers.py
liualgotrader/producer.py
liualgotrader/reprocess/__init__.py
liualgotrader/reprocess/portfolio.py
liualgotrader-0.4.35.dist-info/entry_points.txt
liualgotrader-0.4.35.dist-info/WHEEL
liualgotrader-0.4.35.dist-info/METADATA
liualgotrader-0.4.35.dist-info/licenses/LICENSE
liualgotrader-0.4.35.dist-info/licenses/AUTHORS
liualgotrader-0.4.35.dist-info/RECORD
