Metadata-Version: 2.1
Name: liualgotrader
Version: 0.4.35
Summary: a Pythonic all-batteries-included framework for effective algorithmic trading. The framework is intended to simplify development, testing, deployment and evaluating algo trading strategies.
License: MIT
Author-email: AMOR71 <amor71@sgeltd.com>
Requires-Python: >=3.10
Classifier: Operating System :: OS Independent
Classifier: Programming Language :: Python :: 3.10
Classifier: Programming Language :: Python :: 3.11
Classifier: Programming Language :: Python :: 3.9
Requires-Dist: aiohttp>=3.8.3
Requires-Dist: alpaca-trade-api
Requires-Dist: asyncpg
Requires-Dist: deprecated
Requires-Dist: empyrical
Requires-Dist: finnhub-python
Requires-Dist: fire
Requires-Dist: iso8601
Requires-Dist: matplotlib
Requires-Dist: nest-asyncio
Requires-Dist: numpy
Requires-Dist: pandas-market-calendars
Requires-Dist: parsedatetime
Requires-Dist: polygon-api-client
Requires-Dist: psutil
Requires-Dist: pygit2
Requires-Dist: quantstats
Requires-Dist: requests
Requires-Dist: scipy
Requires-Dist: stockstats
Requires-Dist: streamlit
Requires-Dist: tabulate
Requires-Dist: toml
Requires-Dist: tqdm
Requires-Dist: urllib3
Provides-Extra: dev
Requires-Dist: therapist>=2.2.0; extra == "dev"
Requires-Dist: pytest>=7.2.0; extra == "dev"
Requires-Dist: pytest-asyncio>=0.20.3; extra == "dev"
Requires-Dist: hypothesis>=6.60.0; extra == "dev"
Requires-Dist: mypy>=0.991; extra == "dev"
Requires-Dist: black>=22.12.0; extra == "dev"
Requires-Dist: autoflake>=2.0.0; extra == "dev"
Requires-Dist: bandit>=1.7.4; extra == "dev"
Requires-Dist: isort>=5.11.4; extra == "dev"
Requires-Dist: types-pytz>=2022.7.0.0; extra == "dev"
Requires-Dist: types-requests>=2.28.11.7; extra == "dev"
Requires-Dist: types-tabulate>=0.9.0.0; extra == "dev"
Requires-Dist: types-toml>=0.10.8.1; extra == "dev"
Requires-Dist: sphinx>=6.1.2; extra == "dev"
Requires-Dist: coverage>=7.0.4; extra == "dev"
Requires-Dist: pytest-codecov>=0.5.1; extra == "dev"
Requires-Dist: codecov>=2.1.12; extra == "dev"
